gitinsights/__init__.py
gitinsights/mods/__init__.py
gitinsights/mods/kv_client.py
gitinsights/mods/clients/__init__.py
gitinsights/mods/clients/ado/__init__.py
gitinsights/mods/clients/ado/comments.py
gitinsights/mods/clients/ado/commits.py
gitinsights/mods/clients/ado/entitlements.py
gitinsights/mods/clients/ado/pull_request.py
gitinsights/mods/clients/ado/workitems.py
gitinsights/mods/managers/__init__.py
gitinsights/mods/managers/ado.py
gitinsights/mods/managers/repo_insights_base.py
gitinsights/tests/__init__.py
gitinsights/tests/unit/__init__.py
gitinsights/tests/unit/managers/__init__.py
gitinsights/tests/unit/managers/ado/__init__.py
gitinsights/tests/unit/managers/ado/test_ado_services.py
gitinsights-0.0.6.1.dist-info/LICENSE
gitinsights-0.0.6.1.dist-info/METADATA
gitinsights-0.0.6.1.dist-info/WHEEL
gitinsights-0.0.6.1.dist-info/top_level.txt
gitinsights-0.0.6.1.dist-info/RECORD
