Metadata-Version: 2.1
Name: gitinsights
Version: 0.0.6.1
Summary: A toolset enabling engineering leads to gain insights around how a team is collaborating towards a projects workitems and codebase
Home-page: https://github.com/erikschlegel/git-insights
Author: Erik Schlegel
Author-email: erisch@microsoft.com
License: UNKNOWN
Platform: UNKNOWN
Classifier: Programming Language :: Python :: 3.8
Classifier: License :: OSI Approved :: MIT License
Classifier: Operating System :: OS Independent
Requires-Python: >=3.8.*
Requires-Dist: azure-functions (==1.4.0)
Requires-Dist: requests (==2.22.0)
Requires-Dist: azure-identity (==1.4.1)
Requires-Dist: azure-keyvault-secrets (==4.2.0)
Requires-Dist: azure-core (==1.8.2)
Requires-Dist: azure-common (==1.1.25)
Requires-Dist: pandas (==1.1.3)
Requires-Dist: numpy
Provides-Extra: dev
Requires-Dist: pylint (==2.6.0) ; extra == 'dev'
Requires-Dist: codecov (==2.0.15) ; extra == 'dev'
Requires-Dist: flake8 (==3.7.7) ; extra == 'dev'
Requires-Dist: isort (==4.3.10) ; extra == 'dev'
Requires-Dist: mypy-extensions (==0.4.3) ; extra == 'dev'
Requires-Dist: mypy (==0.790) ; extra == 'dev'
Requires-Dist: pydocstyle (==3.0.0) ; extra == 'dev'
Requires-Dist: pytest (==4.3.1) ; extra == 'dev'
Requires-Dist: pytest-cov (==2.6.1) ; extra == 'dev'
Requires-Dist: setuptools (==41.0.1) ; extra == 'dev'
Requires-Dist: wheel (==0.35.1) ; extra == 'dev'
Requires-Dist: pycodestyle (==2.5.0) ; extra == 'dev'
